[
	{
		"__TYPE__": "SharedSliceContent",
		"variation": "default",
		"primary": {
			"heading": {
				"__TYPE__": "StructuredTextContent",
				"value": [
					{
						"type": "heading2",
						"content": {
							"text": "Expression"
						}
					}
				]
			},
			"description": {
				"__TYPE__": "StructuredTextContent",
				"value": [
					{
						"type": "paragraph",
						"content": {
							"text": "Ad id commodo ut aliqua sit nostrud eiusmod aliquip reprehenderit fugiat officia aute."
						}
					}
				]
			},
			"image": {
				"origin": {
					"id": "main",
					"url": "https://images.unsplash.com/photo-1471897488648-5eae4ac6686b",
					"width": 3560,
					"height": 5340
				},
				"url": "https://images.unsplash.com/photo-1471897488648-5eae4ac6686b",
				"width": 3560,
				"height": 5340,
				"edit": {
					"zoom": 1,
					"crop": {
						"x": 0,
						"y": 0
					},
					"background": "transparent"
				},
				"alt": "plenty",
				"credits": null,
				"__TYPE__": "ImageContent",
				"thumbnails": {}
			},
			"fragrance": {
				"__TYPE__": "LinkContent",
				"key": "cc756c29-4682-4d96-836a-1c7604325971",
				"value": {
					"__TYPE__": "DocumentLink",
					"id": "mock_document_id"
				}
			}
		},
		"items": []
	}
]